dsutil/__init__.py
dsutil/categories.py
dsutil/general.py
dsutil/plotting.py
dsutil-0.2.1.dist-info/LICENSE
dsutil-0.2.1.dist-info/METADATA
dsutil-0.2.1.dist-info/WHEEL
dsutil-0.2.1.dist-info/top_level.txt
dsutil-0.2.1.dist-info/RECORD
