Metadata-Version: 2.1
Name: dsutil
Version: 0.2.1
Summary: Collection of utils for making your life easier when using the Python data science stack
Home-page: https://github.com/queirozfcom/python-ds-util
Author: Felipe Almeida
Author-email: queirozfcom@gmail.com
License: UNKNOWN
Platform: UNKNOWN
Classifier: Programming Language :: Python :: 3
Classifier: License :: OSI Approved :: MIT License
Classifier: Operating System :: OS Independent
Requires-Dist: matplotlib (<4.0.0,>=2.0.0)
Requires-Dist: pandas (>=0.20.0)
Requires-Dist: scikit-learn (>=0.20.0)
